{
  "name": "研报-个股分析",
  "type": "专家研报",
  "style": "purple",
  "updateTime": "2026-05-11 18:00",
  "author": "lobster-research",
  "parameters": {
    "stockAndMarket": "A股/港股/美股，个股",
    "observationCycle": "1-4周（短中期）",
    "observationMode": "单一个股多维度分析 + 交易策略"
  },
  "recommendedKeywords": [
    "个股分析",
    "技术面诊断",
    "基本面拆解",
    "资金面透视",
    "估值定价",
    "交易策略",
    "止损止盈",
    "多空博弈"
  ],
  "recommendedDataSources": [
    "东方财富",
    "同花顺",
    "Wind",
    "财报说明书",
    "交易所公告",
    "龙虎榜数据",
    "中登公司",
    "中证指数"
  ],
  "dataRequirements": "实时行情数据、K线技术指标、个股基本面数据、机构评级及目标价、资金流向数据、龙虎榜、融资融券",
  "coreIdea": "通过对目标个股进行行情技术面、基本面业绩、资金面博弈、估值定价、行业竞争、催化剂事件等多维度综合分析，给出具体可执行的交易策略（买点区间、卖点区间、仓位管理、止损止盈），以操作建议驱动报告价值。",
  "promptBody": "个股深度研报（5000字）\n\n---\n\n前置导读模块\n\n1. 多空攻防态势（技术形态+资金博弈+情绪温度）\n- 段落① 150字，高亮 50字，表1 25行，段落② 150字\n- 聚焦：当前多空力量对比、关键支撑阻力位、成交量能变化、市场情绪指标、短期博弈格局\n\n2. 投资导航（多周期策略矩阵）\n- 段落① 150字，高亮 50字，表1 25行，段落② 150字\n- 聚焦：短/中/长期各维度策略定位、当前处于什么阶段（筑底/主升/盘整/回调）、仓位配置总纲\n\n3. 个股快照（核心指标一览+AI速读）\n- 段落① 150字，高亮 50字，无表格，段落② 150字\n- 聚焦：本周/双周个股重大动态（异动/公告/新闻）、核心数据速览、阶段性总结\n\n---\n\n第一章 行情技术面诊断（K线形态｜量价关系｜均线系统｜技术指标）\n\n- 段落① 150字，高亮 50字，表1 25行（量价关键位矩阵），段落② 150字\n- 内容：K线组合形态研判、MA排列与趋势方向判断、成交量能分析（放量/缩量/异常量）、MACD/KDJ/RSI等技术指标信号、短/中/长期趋势综合评分、关键支撑位与阻力位\n\n---\n\n第二章 基本面业绩拆解（营收利润｜业务结构｜利润率变动）\n\n- 段落① 150字，高亮 50字，无表格，段落② 150字\n- 内容：近期财报核心数据解读（营收/利润/毛利率/净利率同比环比变化）、业务板块分化分析、利润率变动原因归因（产品结构/成本/竞争）、研报期内的业绩预期与市场预期差\n\n---\n\n第三章 资金面全景透视（主力流向｜北向资金｜融资融券｜龙虎榜）\n\n- 段落① 150字，高亮 50字，表1 25行（资金流向数据汇总），段落② 150字\n- 内容：主力资金近期净流入/流出趋势、北向资金持仓变化、融资融券余额变化、龙虎榜席位买卖逻辑、大宗交易/增减持信号、股东户数变化\n\n---\n\n第四章 估值定价模型（PE/PB分位｜PEG｜DCF｜目标价区间）\n\n- 段落① 150字，高亮 50字，表1 25行（多模型估值对比），段落② 150字\n- 内容：PE（TTM/静态/前瞻）与历史分位对比、PB/PS与行业对比、PEG估值合理性判断、机构目标价分布（最高/最低/均值/中位数）、DCF情景测算（乐观/基准/悲观）、当前价格对应的估值状态\n\n---\n\n第五章 行业景气与竞争定位（行业趋势｜份额变化｜相对优势）\n\n- 段落① 150字，高亮 50字，无表格，段落② 150字\n- 内容：所属行业当前景气周期位置（上行/触底/下行）、行业内市场份额及变化趋势、相较主要竞争对手的核心优势/短板、行业政策面影响\n\n---\n\n第六章 催化剂与事件驱动（财报节点｜产品发布｜政策催化 | 消息日历）\n\n- 段落① 150字，高亮 50字，表1 25行（未来事件日历），段落② 150字\n- 内容：近期已知的重大催化剂（财报公布/新产品发布/重大合同/政策落地）、潜在催化剂预期、按时间线排列的事件日历、每个事件对股价的可能影响方向及幅度预估\n\n---\n\n第七章 风险全景（个股特有风险｜大盘系统性风险｜黑天鹅预案）\n\n- 段落① 150字，高亮 50字，表1 25行（风险热力图），段落② 150字\n- 内容：个股层面风险（业绩不达预期/管理层变动/减持/监管处罚）、宏观系统性风险（利率/汇率/政策转向）、黑天鹅情景压力测试、不同情景下的应对预案\n\n---\n\n第八章 交易策略与执行清单（买点区间｜卖点区间｜仓位管理｜止损止盈｜条件单）\n\n- 段落① 150字，高亮 50字，表1 25行（交易执行清单），段落② 150字\n- 内容：具体买点区间（技术面+基本面双验证）、分档建仓方案（首次/加仓/重仓触发条件）、止损价设定与依据（关键技术位/百分比止损）、分档止盈目标价（保守/中性/乐观目标）、持股周期预期、条件单设置建议\n\n---\n\n第九章 动态跟踪框架（关键里程碑｜复盘checklist｜调整触发条件）\n\n- 段落① 150字，高亮 50字，表1 25行（监测指标清单），段落② 150字\n- 内容：下一交易周/月核心监测事件、技术面关键价位突破/跌破信号、基本面数据公布时点对应的仓位调整规则、每周复盘checklist\n\n---\n\n收尾板块\n\n核心摘要 + 策略寄语\n- 独立段落 150字，高亮 50字，无表格\n- 风格：3句话总结核心逻辑+具体操作方向+一句警醒\n\n---\n\n页脚固定栏\n\n- 数据来源（东方财富、同花顺、Wind、财报说明书、交易所公告、龙虎榜、中登公司）\n- 资讯核实声明\n- 风险提示（个股波动风险、信息时效性、政策不确定性）\n- 免责说明",
  "sections": [
    {
      "title": "🦞 多空攻防与投资导航",
      "subsections": [
        {
          "title": "近期表现",
          "content": "_基于2_stock_quote_realtime.json和2_stock_kline_indicator.json的行情技术面诊断，200-300字",
          "table": "_Agent 填充表格数据（格式：{headers:[...], rows:[[...]]}）",
          "highlight": "_核心判断一句话"
        },
        {
          "title": "多空态势与策略矩阵",
          "content": "_基于技术面+资金面+基本面综合评估短/中/长期策略方向，300字",
          "highlight": "_核心判断一句话"
        }
      ]
    },
    {
      "title": "一、行情技术面深度诊断",
      "subsections": [
        {
          "title": "K线形态与均线系统",
          "content": "_K线组合、MA排列、量价关系分析，250字",
          "table": {
            "headers": [
              "指标",
              "数值",
              "信号",
              "趋势判断"
            ],
            "rows": [
              [
                "MA5/MA10/MA20",
                "_/_/_",
                "_信号",
                "_趋势"
              ],
              [
                "短期趋势/中期/长期",
                "_/_/_",
                "_信号",
                "_评分"
              ],
              [
                "支撑位/阻力位",
                "_/_",
                "_信号",
                "_有效位"
              ],
              [
                "成交量能",
                "_日/5日均量对比",
                "_",
                "_"
              ]
            ]
          },
          "highlight": "_核心判断一句话"
        },
        {
          "title": "技术指标综合评分",
          "content": "_MACD/KDJ/RSI/布林带等指标信号汇总评分，150字",
          "highlight": "_核心判断一句话"
        }
      ]
    },
    {
      "title": "二、基本面业绩拆解",
      "subsections": [
        {
          "title": "营收利润与利润率变动",
          "content": "_近1-2期财报营收利润/毛利率/净利率同比环比变化及原因分析，300字",
          "table": {
            "headers": [
              "指标",
              "上期",
              "本期",
              "同比",
              "环比"
            ],
            "rows": [
              [
                "营收(亿元)",
                "_",
                "_",
                "_",
                "_"
              ],
              [
                "归母净利(亿元)",
                "_",
                "_",
                "_",
                "_"
              ],
              [
                "毛利率",
                "_",
                "_",
                "_",
                "_"
              ],
              [
                "净利率",
                "_",
                "_",
                "_",
                "_"
              ]
            ]
          },
          "highlight": "_核心判断一句话"
        },
        {
          "title": "业务结构与利润率归因",
          "content": "_各业务板块收入变化、利润率变动的结构性原因（产品结构/成本/竞争），200字",
          "highlight": "_核心判断一句话"
        }
      ]
    },
    {
      "title": "三、资金面全景透视",
      "subsections": [
        {
          "title": "主力资金与北向资金",
          "content": "_近期主力资金净流入/流出、北向资金持仓变化分析，200字",
          "highlight": "_核心判断一句话"
        },
        {
          "title": "融资融券与龙虎榜",
          "content": "_融资融券余额变化、龙虎榜席位逻辑、大宗交易/增减持信号，150字",
          "table": {
            "headers": [
              "资金维度",
              "数据",
              "方向",
              "信号"
            ],
            "rows": [
              [
                "主力资金近5日",
                "_",
                "_",
                "_"
              ],
              [
                "北向资金持仓",
                "_",
                "_",
                "_"
              ],
              [
                "融资余额变化",
                "_",
                "_",
                "_"
              ],
              [
                "龙虎榜/大宗",
                "_",
                "_",
                "_"
              ]
            ]
          },
          "highlight": "_核心判断一句话"
        }
      ]
    },
    {
      "title": "四、估值定价模型",
      "subsections": [
        {
          "title": "多维度估值对比",
          "content": "_PE/PB/PS/PEG历史分位对比、机构目标价分布，250字",
          "table": {
            "headers": [
              "方法",
              "当前值",
              "历史中枢",
              "行业均值",
              "判断"
            ],
            "rows": [
              [
                "PE(TTM)",
                "_",
                "_",
                "_",
                "_"
              ],
              [
                "PB",
                "_",
                "_",
                "_",
                "_"
              ],
              [
                "PEG",
                "_",
                "_",
                "_",
                "_"
              ],
              [
                "机构目标均价",
                "_",
                "_",
                "_",
                "_"
              ]
            ]
          },
          "highlight": "_核心判断一句话"
        },
        {
          "title": "目标价区间与估值状态",
          "content": "_机构目标价最高/最低/均值、DCF情景测算、当前估值状态评估，200字",
          "highlight": "_核心判断一句话"
        }
      ]
    },
    {
      "title": "五、行业景气与竞争定位",
      "subsections": [
        {
          "title": "行业景气度判断",
          "content": "_所属行业当前景气周期位置、近期行业趋势变化，200字",
          "table": "_Agent 填充表格数据（格式：{headers:[...], rows:[[...]]}）",
          "highlight": "_核心判断一句话"
        },
        {
          "title": "竞争地位评估",
          "content": "_核心竞争优势/短板、与主要竞争对手对比分析，200字",
          "highlight": "_核心判断一句话"
        }
      ]
    },
    {
      "title": "六、催化剂与风险全景",
      "subsections": [
        {
          "title": "催化剂与事件日历",
          "content": "_近期已知及潜在的催化事件（财报/产品/政策/合同），按时间线排列，200字",
          "highlight": "_核心判断一句话"
        },
        {
          "title": "风险矩阵与应对预案",
          "content": "_个股特有风险/宏观系统性风险/黑天鹅情景及应对措施，200字",
          "table": {
            "headers": [
              "风险类别",
              "描述",
              "影响",
              "概率",
              "应对预案"
            ],
            "rows": [
              [
                "_",
                "_",
                "_",
                "_",
                "_"
              ]
            ]
          },
          "highlight": "_核心判断一句话"
        }
      ]
    },
    {
      "title": "七、交易策略与执行清单",
      "subsections": [
        {
          "title": "买卖点与仓位管理",
          "content": "_具体买点区间/分档建仓方案/止损价设定/分档止盈目标/持股周期，300字",
          "table": {
            "headers": [
              "操作项",
              "条件",
              "仓位",
              "目标价/止损价"
            ],
            "rows": [
              [
                "首次建仓",
                "_",
                "_%",
                "_"
              ],
              [
                "加仓触发",
                "_",
                "_%",
                "_"
              ],
              [
                "第一止盈",
                "_",
                "减仓至_%",
                "_"
              ],
              [
                "第二止盈",
                "_",
                "减仓至_%",
                "_"
              ],
              [
                "止损线",
                "_",
                "清仓",
                "_"
              ]
            ]
          },
          "highlight": "_核心判断一句话"
        },
        {
          "title": "条件单与执行纪律",
          "content": "_条件单设置建议、执行纪律（不追高/不加仓/止损不犹豫），150字",
          "highlight": "_核心判断一句话"
        }
      ]
    },
    {
      "title": "八、动态跟踪框架",
      "subsections": [
        {
          "title": "关键监测清单",
          "content": "_未来1-4周核心监测事件、技术面关键位、仓位调整触发条件、每周复盘checklist，200字",
          "table": {
            "headers": [
              "监测时点",
              "指标",
              "利好信号",
              "利空信号"
            ],
            "rows": [
              [
                "持续",
                "关键技术位",
                "突破_",
                "跌破_"
              ],
              [
                "持续",
                "成交量变化",
                "放量_",
                "缩量_"
              ],
              [
                "下一事件",
                "_",
                "_",
                "_"
              ]
            ]
          },
          "highlight": "_核心判断一句话"
        }
      ]
    }
  ]
}